CPSReleaseTool/finalv1.py
CPSReleaseTool/pdfwordgui_support.py
CPSReleaseTool-1.0.0.dist-info/LICENSE.txt
CPSReleaseTool-1.0.0.dist-info/METADATA
CPSReleaseTool-1.0.0.dist-info/WHEEL
CPSReleaseTool-1.0.0.dist-info/top_level.txt
CPSReleaseTool-1.0.0.dist-info/RECORD
